social_distancing_sim/__init__.py
social_distancing_sim/agent/__init__.py
social_distancing_sim/agent/learning_agent_base.py
social_distancing_sim/agent/non_learning_agent_base.py
social_distancing_sim/agent/basic_agents/__init__.py
social_distancing_sim/agent/basic_agents/dummy_agent.py
social_distancing_sim/agent/basic_agents/isolation_agent.py
social_distancing_sim/agent/basic_agents/masking_agent.py
social_distancing_sim/agent/basic_agents/random_agent.py
social_distancing_sim/agent/basic_agents/treatment_agent.py
social_distancing_sim/agent/basic_agents/vaccination_agent.py
social_distancing_sim/agent/multi_agents/__init__.py
social_distancing_sim/agent/multi_agents/multi_agent.py
social_distancing_sim/agent/policy_agents/__init__.py
social_distancing_sim/agent/policy_agents/distancing_policy_agent.py
social_distancing_sim/agent/policy_agents/masking_policy_agent.py
social_distancing_sim/agent/policy_agents/treatment_policy_agent.py
social_distancing_sim/agent/policy_agents/vaccination_policy_agent.py
social_distancing_sim/agent/rl_agents/__init__.py
social_distancing_sim/agent/rl_agents/rlk_agent_configs.py
social_distancing_sim/agent/rl_agents/models/__init__.py
social_distancing_sim/agent/rl_agents/models/targeted_nn.py
social_distancing_sim/agent/rl_agents/models/untargeted_nn.py
social_distancing_sim/agent/rl_agents/q_learning/__init__.py
social_distancing_sim/agent/rl_agents/q_learning/dqn_untargeted.py
social_distancing_sim/environment/__init__.py
social_distancing_sim/environment/action_space.py
social_distancing_sim/environment/disease.py
social_distancing_sim/environment/environment.py
social_distancing_sim/environment/environment_plotting.py
social_distancing_sim/environment/graph.py
social_distancing_sim/environment/healthcare.py
social_distancing_sim/environment/history.py
social_distancing_sim/environment/observation_space.py
social_distancing_sim/environment/scoring.py
social_distancing_sim/environment/status.py
social_distancing_sim-0.11.2.dist-info/METADATA
social_distancing_sim-0.11.2.dist-info/WHEEL
social_distancing_sim-0.11.2.dist-info/top_level.txt
social_distancing_sim-0.11.2.dist-info/RECORD
