Metadata-Version: 2.1
Name: social_distancing_sim
Version: 0.11.2
Author-email: Gareth Jones  <garethgithub@gmail.com>
Project-URL: Homepage, https://github.com/garethjns/social-distancing-sim
Project-URL: Repository, https://github.com/garethjns/social-distancing-sim
Classifier: Programming Language :: Python :: 3.9
Classifier: Programming Language :: Python :: 3.10
Classifier: Programming Language :: Python :: 3.11
Classifier: Operating System :: OS Independent
Requires-Python: >=3.9
Requires-Dist: networkx
Requires-Dist: numpy<=1.23
Requires-Dist: matplotlib
Requires-Dist: imageio
Requires-Dist: dataclasses
Requires-Dist: seaborn<=0.13
Requires-Dist: tqdm
Requires-Dist: joblib
Requires-Dist: pandas
Requires-Dist: mlflow
Requires-Dist: gym>=0.26
Requires-Dist: uvicorn
Requires-Dist: aiofiles
Provides-Extra: rlk
Requires-Dist: reinforcement-learning-keras==0.5.1; extra == "rlk"
Provides-Extra: fastapi
Requires-Dist: fastapi; extra == "fastapi"
Provides-Extra: gradio
Requires-Dist: gradio; extra == "gradio"
Provides-Extra: dev
Requires-Dist: pytest; extra == "dev"
Requires-Dist: pre-commit; extra == "dev"
